the_unix_manager/__init__.py
the_unix_manager/the_unix_manager.py
theUnixManager-1.0.0.dist-info/LICENSE.md
theUnixManager-1.0.0.dist-info/METADATA
theUnixManager-1.0.0.dist-info/WHEEL
theUnixManager-1.0.0.dist-info/top_level.txt
theUnixManager-1.0.0.dist-info/RECORD
